openrpc/__init__.py
openrpc/_common.py
openrpc/_depends.py
openrpc/_discover.py
openrpc/_method_processor.py
openrpc/_method_registrar.py
openrpc/_objects.py
openrpc/_request_processor.py
openrpc/_router.py
openrpc/_server.py
openrpc/py.typed
openrpc-10.5.0.dist-info/LICENSE
openrpc-10.5.0.dist-info/METADATA
openrpc-10.5.0.dist-info/WHEEL
openrpc-10.5.0.dist-info/RECORD
