Metadata-Version: 2.3
Name: openrpc
Version: 10.5.0
Summary: Transport agnostic framework for developing OpenRPC servers.
License: MIT
Author: Matthew Burkard
Author-email: matthewjburkard@gmail.com
Requires-Python: >=3.9,<4.0
Classifier: Intended Audience :: Developers
Classifier: License :: OSI Approved :: MIT License
Classifier: Programming Language :: Python :: 3
Classifier: Programming Language :: Python :: 3.9
Classifier: Programming Language :: Python :: 3.10
Classifier: Programming Language :: Python :: 3.11
Classifier: Programming Language :: Python :: 3.12
Classifier: Programming Language :: Python :: 3.13
Classifier: Topic :: Software Development
Classifier: Topic :: Software Development :: Libraries
Classifier: Topic :: Software Development :: Libraries :: Python Modules
Classifier: Typing :: Typed
Requires-Dist: jsonrpc2-objects (>=4.2.0,<5.0.0)
Requires-Dist: lorem-pysum (>=1.4.7,<2.0.0)
Requires-Dist: py-undefined (>=0.1.7,<0.2.0)
Requires-Dist: pydantic (>=2.4.2,<3.0.0)
Project-URL: Homepage, https://python-openrpc.burkard.cloud
Project-URL: Repository, https://gitlab.com/mburkard/openrpc
